Metadata-Version: 2.1
Name: para-gen
Version: 93.6
Summary: x
Author: x
Author-email: xxx@outlook.com
Requires-Dist: requests
Requires-Dist: psutil
